assets/2025-02-27_04-01.png
assets/2025-02-27_04-01_1.png
assets/2025-02-27_04-02.png
assets/readme.webp
tests/__init__.py
tests/test.py
torch_jpeg_blockiness/__init__.py
torch_jpeg_blockiness/blockiness.py
torch_jpeg_blockiness/example_usage.py
torch_jpeg_blockiness/original_blockiness.py
torch_jpeg_blockiness/visualize_metrics.py
torch_jpeg_blockiness-1.0.4.dist-info/LICENCE
torch_jpeg_blockiness-1.0.4.dist-info/METADATA
torch_jpeg_blockiness-1.0.4.dist-info/WHEEL
torch_jpeg_blockiness-1.0.4.dist-info/top_level.txt
torch_jpeg_blockiness-1.0.4.dist-info/RECORD
