Metadata-Version: 2.2
Name: torch_jpeg_blockiness
Version: 1.0.4
Summary: The higher the blockiness metric value, the more likely it is that the image was JPEG-compressed at a low quality. Re-implementation of blockiness from "Rethinking Image Super-Resolution from Training Data Perspectives"
Author-email: Matej Ciglenečki <matej.ciglenecki@gmail.com>
Project-URL: Homepage, https://github.com/ciglenecki/torch-jpeg-blockiness
Project-URL: Issues, https://github.com/ciglenecki/torch-jpeg-blockinessissues
Requires-Python: >=3.10
License-File: LICENCE
Requires-Dist: torch==2.6.*
Requires-Dist: numpy==2.2.*
